analysis/__init__.py
analysis/plotHelper.py
analysis/plotting.py
utilities/__init__.py
utilities/chemistryUtilities.py
utilities/dataframeUtilities.py
utilities/dictUtilities.py
utilities/listUtilities.py
utilities/numerics.py
utilities/astroTools/__init__.py
utilities/astroTools/spectralUtilities.py
sd_tools_SADESHMUKH-0.0.1.dist-info/LICENSE.txt
sd_tools_SADESHMUKH-0.0.1.dist-info/METADATA
sd_tools_SADESHMUKH-0.0.1.dist-info/WHEEL
sd_tools_SADESHMUKH-0.0.1.dist-info/top_level.txt
sd_tools_SADESHMUKH-0.0.1.dist-info/RECORD
